rezume/__init__.py
rezume/assets/rezume-template.yml
rezume/base.py
rezume/cli/__init__.py
rezume/cli/commands/__init__.py
rezume/cli/commands/init.py
rezume/cli/commands/serve/__init__.py
rezume/cli/commands/serve/itty3.py
rezume/cli/commands/test.py
rezume/models.py
rezume/sections.py
rezume-0.4.2.dist-info/entry_points.txt
rezume-0.4.2.dist-info/LICENSE
rezume-0.4.2.dist-info/WHEEL
rezume-0.4.2.dist-info/METADATA
rezume-0.4.2.dist-info/RECORD
