Metadata-Version: 2.1
Name: rezume
Version: 0.4.2
Summary: Rezume, validate and create text-based resumes easily.
Home-page: https://github.com/hkmshb/rezume.git
License: BSD-2-Clause
Keywords: resume,rezume
Author: Abdul-Hakeem Shaibu
Author-email: s.abdulhakeeem@gmail.com
Requires-Python: >=3.6,<4.0
Classifier: License :: OSI Approved :: BSD License
Classifier: Programming Language :: Python :: 3
Classifier: Programming Language :: Python :: 3.6
Classifier: Programming Language :: Python :: 3.7
Classifier: Programming Language :: Python :: 3.8
Classifier: Programming Language :: Python :: 3.9
Requires-Dist: pydantic[email] (>=1.7.3,<2.0.0)
Requires-Dist: pyyaml (>=5.4.1,<6.0.0)
Requires-Dist: typer[all] (>=0.3.2,<0.4.0)
Project-URL: Repository, https://github.com/hkmshb/rezume.git
